<?xml version="1.0" encoding="UTF-8"?><COMPONENTS author="gkovalev" description="" name="test.onevizion.com_BPL_11072021192732.xml" site="http&#x3a;&#x2f;&#x2f;dev2.vqs.net&#x3a;8080" ts="" ><XITOR_TYPES>
 <XITOR_TYPES_ITEM>
  <APPLET_LABEL>
   <T_LABEL>
    <APP_LANG_ID>0</APP_LANG_ID>
    <APP_LABEL_ID>-3985226</APP_LABEL_ID>
    <LABEL_TEXT>Test1</LABEL_TEXT>
   </T_LABEL>
   <T_LABEL>
    <APP_LANG_ID>1</APP_LANG_ID>
    <APP_LABEL_ID>-3985226</APP_LABEL_ID>
    <LABEL_TEXT>Test1</LABEL_TEXT>
   </T_LABEL>
   <T_LABEL>
    <APP_LANG_ID>5</APP_LANG_ID>
    <APP_LABEL_ID>-3985226</APP_LABEL_ID>
    <LABEL_TEXT>Test1</LABEL_TEXT>
   </T_LABEL>
   <T_LABEL>
    <APP_LANG_ID>10</APP_LANG_ID>
    <APP_LABEL_ID>-3985226</APP_LABEL_ID>
    <LABEL_TEXT>Test1</LABEL_TEXT>
   </T_LABEL>
   <T_LABEL>
    <APP_LANG_ID>20</APP_LANG_ID>
    <APP_LABEL_ID>-3985226</APP_LABEL_ID>
    <LABEL_TEXT>Test1</LABEL_TEXT>
   </T_LABEL>
  </APPLET_LABEL>
  <CAN_BE_A_TEMPLATE>0</CAN_BE_A_TEMPLATE>
  <IS_CLONING_ALLOWED>0</IS_CLONING_ALLOWED>
  <IS_EFILE_CONTAINER>0</IS_EFILE_CONTAINER>
  <IS_STATIC_DEFINITION>0</IS_STATIC_DEFINITION>
  <IS_USER>0</IS_USER>
  <KEY_FIELD>XITOR_ID</KEY_FIELD>
  <MYXITORS_LABEL>
   <T_LABEL>
    <APP_LANG_ID>0</APP_LANG_ID>
    <APP_LABEL_ID>-3985228</APP_LABEL_ID>
    <LABEL_TEXT>Test1</LABEL_TEXT>
   </T_LABEL>
   <T_LABEL>
    <APP_LANG_ID>1</APP_LANG_ID>
    <APP_LABEL_ID>-3985228</APP_LABEL_ID>
    <LABEL_TEXT>My Test1</LABEL_TEXT>
   </T_LABEL>
   <T_LABEL>
    <APP_LANG_ID>5</APP_LANG_ID>
    <APP_LABEL_ID>-3985228</APP_LABEL_ID>
    <LABEL_TEXT>Test1</LABEL_TEXT>
   </T_LABEL>
   <T_LABEL>
    <APP_LANG_ID>10</APP_LANG_ID>
    <APP_LABEL_ID>-3985228</APP_LABEL_ID>
    <LABEL_TEXT>Test1</LABEL_TEXT>
   </T_LABEL>
   <T_LABEL>
    <APP_LANG_ID>20</APP_LANG_ID>
    <APP_LABEL_ID>-3985228</APP_LABEL_ID>
    <LABEL_TEXT>Test1</LABEL_TEXT>
   </T_LABEL>
  </MYXITORS_LABEL>
  <OBJ_DISPLAY_FIELDS/>
  <PREFIX_LABEL>
   <T_LABEL>
    <APP_LANG_ID>0</APP_LANG_ID>
    <APP_LABEL_ID>-3985227</APP_LABEL_ID>
    <LABEL_TEXT>T1</LABEL_TEXT>
   </T_LABEL>
   <T_LABEL>
    <APP_LANG_ID>1</APP_LANG_ID>
    <APP_LABEL_ID>-3985227</APP_LABEL_ID>
    <LABEL_TEXT>T1</LABEL_TEXT>
   </T_LABEL>
   <T_LABEL>
    <APP_LANG_ID>5</APP_LANG_ID>
    <APP_LABEL_ID>-3985227</APP_LABEL_ID>
    <LABEL_TEXT>T1</LABEL_TEXT>
   </T_LABEL>
   <T_LABEL>
    <APP_LANG_ID>10</APP_LANG_ID>
    <APP_LABEL_ID>-3985227</APP_LABEL_ID>
    <LABEL_TEXT>T1</LABEL_TEXT>
   </T_LABEL>
   <T_LABEL>
    <APP_LANG_ID>20</APP_LANG_ID>
    <APP_LABEL_ID>-3985227</APP_LABEL_ID>
    <LABEL_TEXT>T1</LABEL_TEXT>
   </T_LABEL>
  </PREFIX_LABEL>
  <TABLE_NAME>XITOR</TABLE_NAME>
  <XITORID_LABEL>
   <T_LABEL>
    <APP_LANG_ID>0</APP_LANG_ID>
    <APP_LABEL_ID>-3985229</APP_LABEL_ID>
    <LABEL_TEXT>Test1</LABEL_TEXT>
   </T_LABEL>
   <T_LABEL>
    <APP_LANG_ID>1</APP_LANG_ID>
    <APP_LABEL_ID>-3985229</APP_LABEL_ID>
    <LABEL_TEXT>Test1 ID</LABEL_TEXT>
   </T_LABEL>
   <T_LABEL>
    <APP_LANG_ID>5</APP_LANG_ID>
    <APP_LABEL_ID>-3985229</APP_LABEL_ID>
    <LABEL_TEXT>Test1</LABEL_TEXT>
   </T_LABEL>
   <T_LABEL>
    <APP_LANG_ID>10</APP_LANG_ID>
    <APP_LABEL_ID>-3985229</APP_LABEL_ID>
    <LABEL_TEXT>Test1</LABEL_TEXT>
   </T_LABEL>
   <T_LABEL>
    <APP_LANG_ID>20</APP_LANG_ID>
    <APP_LABEL_ID>-3985229</APP_LABEL_ID>
    <LABEL_TEXT>Test1</LABEL_TEXT>
   </T_LABEL>
  </XITORID_LABEL>
  <XITOR_CLASS_LABEL>
   <T_LABEL>
    <APP_LANG_ID>0</APP_LANG_ID>
    <APP_LABEL_ID>-3985230</APP_LABEL_ID>
    <LABEL_TEXT>Test1</LABEL_TEXT>
   </T_LABEL>
   <T_LABEL>
    <APP_LANG_ID>1</APP_LANG_ID>
    <APP_LABEL_ID>-3985230</APP_LABEL_ID>
    <LABEL_TEXT>Test1</LABEL_TEXT>
   </T_LABEL>
   <T_LABEL>
    <APP_LANG_ID>5</APP_LANG_ID>
    <APP_LABEL_ID>-3985230</APP_LABEL_ID>
    <LABEL_TEXT>Test1</LABEL_TEXT>
   </T_LABEL>
   <T_LABEL>
    <APP_LANG_ID>10</APP_LANG_ID>
    <APP_LABEL_ID>-3985230</APP_LABEL_ID>
    <LABEL_TEXT>Test1</LABEL_TEXT>
   </T_LABEL>
   <T_LABEL>
    <APP_LANG_ID>20</APP_LANG_ID>
    <APP_LABEL_ID>-3985230</APP_LABEL_ID>
    <LABEL_TEXT>Test1</LABEL_TEXT>
   </T_LABEL>
  </XITOR_CLASS_LABEL>
  <XITOR_TYPE>Test1</XITOR_TYPE>
  <XITOR_TYPE_ID>149323</XITOR_TYPE_ID>
  <XITOR_CLASSES/>
  <TM_SETUPS>
   <T_TM_SETUP>
    <ALIAS_CONFIG_FIELD/>
    <CREATE_NEW_XITOR>0</CREATE_NEW_XITOR>
    <HOST>mail.onevizion.com</HOST>
    <IMAP_PORT>143</IMAP_PORT>
    <IS_ENABLED>0</IS_ENABLED>
    <PATH>INBOX</PATH>
    <POLL_SERVER_EVERY_MINUTE>10</POLL_SERVER_EVERY_MINUTE>
    <REPLAY_ON_FAIL>1</REPLAY_ON_FAIL>
    <REPLY_ON_SUCCESS>0</REPLY_ON_SUCCESS>
    <SPAM_PATH>SPAM</SPAM_PATH>
    <TM_SETUP_ID>1001049082</TM_SETUP_ID>
    <USER_NAME>TrackorMail@onevizion.com</USER_NAME>
    <XITOR_TYPE_ID>149323</XITOR_TYPE_ID>
    <MAPPINGS/>
   </T_TM_SETUP>
  </TM_SETUPS>
  <IS_AUTOKEY>1</IS_AUTOKEY>
  <AUTOKEY_START_AT>0</AUTOKEY_START_AT>
  <AUTOKEY_FORMULA>10010522178/|/|/|1/</AUTOKEY_FORMULA>
  <WP_MODE_ID>1</WP_MODE_ID>
  <PROGRAM_ID>10009255</PROGRAM_ID>
  <FORMULA>
   <FIELD_NAME1>T1_TEXT</FIELD_NAME1>
   <TRACKOR_TYPE1>Test1</TRACKOR_TYPE1>
   <NUM_DIGITS>1</NUM_DIGITS>
  </FORMULA>
  <COMPONENT_PACKAGES>
   <T_BPL_COMP_PKG>
    <COMPONENT_ID>11</COMPONENT_ID>
    <OBJECT_ID>149323</OBJECT_ID>
    <COMPONENTS_PACKAGE_ID>171954</COMPONENTS_PACKAGE_ID>
    <NAME>TEST1</NAME>
    <PROGRAM_ID>10009255</PROGRAM_ID>
    <BPD_ITEMS/>
   </T_BPL_COMP_PKG>
  </COMPONENT_PACKAGES>
  <BPD_ITEMS/>
  <PARENT_RELATION_TYPES>
   <T_BPL_RELATION_TYPE>
    <RELATION_TYPE_ID>100190916</RELATION_TYPE_ID>
    <CHILD_TYPE_ID>149323</CHILD_TYPE_ID>
    <CARDINALITY_ID>2</CARDINALITY_ID>
    <CHILD_REQUIRES_PARENT>0</CHILD_REQUIRES_PARENT>
    <ORDER_NUMBER>100190916</ORDER_NUMBER>
    <ON_PARENT_DELETE_CASCADE>0</ON_PARENT_DELETE_CASCADE>
    <IS_LOCKABLE>0</IS_LOCKABLE>
    <SHOW_ALL_IN_TRCONTAINER>0</SHOW_ALL_IN_TRCONTAINER>
    <USE_IN_SELF_SERVICE_IMP>0</USE_IN_SELF_SERVICE_IMP>
    <CHILD_TRACKOR_TYPE>Test1</CHILD_TRACKOR_TYPE>
    <UNIQUE_BY_XT_ID>149323</UNIQUE_BY_XT_ID>
    <UNIQUE_TRACKOR_TYPE>Test1</UNIQUE_TRACKOR_TYPE>
   </T_BPL_RELATION_TYPE>
  </PARENT_RELATION_TYPES>
  <CHAT_SUPPORTED>0</CHAT_SUPPORTED>
 </XITOR_TYPES_ITEM>
</XITOR_TYPES><CONFIG_FIELDS>
 <CONFIG_FIELDS_ITEM>
  <APP_LABEL>
   <T_LABEL>
    <APP_LANG_ID>0</APP_LANG_ID>
    <APP_LABEL_ID>-3985246</APP_LABEL_ID>
    <LABEL_TEXT>Text</LABEL_TEXT>
   </T_LABEL>
   <T_LABEL>
    <APP_LANG_ID>1</APP_LANG_ID>
    <APP_LABEL_ID>-3985246</APP_LABEL_ID>
    <LABEL_TEXT>Text</LABEL_TEXT>
   </T_LABEL>
   <T_LABEL>
    <APP_LANG_ID>5</APP_LANG_ID>
    <APP_LABEL_ID>-3985246</APP_LABEL_ID>
    <LABEL_TEXT>Text</LABEL_TEXT>
   </T_LABEL>
   <T_LABEL>
    <APP_LANG_ID>10</APP_LANG_ID>
    <APP_LABEL_ID>-3985246</APP_LABEL_ID>
    <LABEL_TEXT>Text</LABEL_TEXT>
   </T_LABEL>
   <T_LABEL>
    <APP_LANG_ID>20</APP_LANG_ID>
    <APP_LABEL_ID>-3985246</APP_LABEL_ID>
    <LABEL_TEXT>Text</LABEL_TEXT>
   </T_LABEL>
  </APP_LABEL>
  <CONFIG_FIELD_ID>10010522178</CONFIG_FIELD_ID>
  <CONFIG_FIELD_NAME>T1_TEXT</CONFIG_FIELD_NAME>
  <DATA_TYPE>0</DATA_TYPE>
  <FIELD_SIZE>1000</FIELD_SIZE>
  <FIELD_WIDTH>180</FIELD_WIDTH>
  <GRID_COLUMN_WIDTH>160</GRID_COLUMN_WIDTH>
  <IMAGE_ROTATE>0</IMAGE_ROTATE>
  <IS_IMAGE_EXTRACT_METADATA>0</IS_IMAGE_EXTRACT_METADATA>
  <IS_LOCKABLE>0</IS_LOCKABLE>
  <IS_MANDATORY>0</IS_MANDATORY>
  <IS_MY_THINGS_MARKER>0</IS_MY_THINGS_MARKER>
  <IS_READ_ONLY>0</IS_READ_ONLY>
  <IS_SEPARATE_THOUSANDS>0</IS_SEPARATE_THOUSANDS>
  <IS_STATIC>0</IS_STATIC>
  <IS_TWO_COLS_SPAN>0</IS_TWO_COLS_SPAN>
  <LOG_BLOB_CHANGES>0</LOG_BLOB_CHANGES>
  <PARENS_FOR_NEGATIVE>0</PARENS_FOR_NEGATIVE>
  <SHORT_NAME_LABEL/>
  <STORE_IN_CLOUD>0</STORE_IN_CLOUD>
  <USE_IN_MY_THINGS_FILTER>0</USE_IN_MY_THINGS_FILTER>
  <TRACKOR_TYPE>Test1</TRACKOR_TYPE>
  <IS_SHOW_SECONDS>0</IS_SHOW_SECONDS>
  <PROGRAM_ID>10009255</PROGRAM_ID>
  <IS_NOT_CLONE_FIELD_VALUE>0</IS_NOT_CLONE_FIELD_VALUE>
  <IS_NOT_CLONE_LOCKS>0</IS_NOT_CLONE_LOCKS>
  <IS_UPLOAD_TO_S3_DIRECTLY>0</IS_UPLOAD_TO_S3_DIRECTLY>
  <IS_SUPPORT_BARCODE>0</IS_SUPPORT_BARCODE>
  <IS_VALIDATION_ENABLED>0</IS_VALIDATION_ENABLED>
  <ERROR_MESSAGE_LABEL/>
  <COMPONENT_PACKAGES>
   <T_BPL_COMP_PKG>
    <COMPONENT_ID>5</COMPONENT_ID>
    <OBJECT_ID>10010522178</OBJECT_ID>
    <COMPONENTS_PACKAGE_ID>171954</COMPONENTS_PACKAGE_ID>
    <NAME>TEST1</NAME>
    <PROGRAM_ID>10009255</PROGRAM_ID>
    <BPD_ITEMS/>
   </T_BPL_COMP_PKG>
  </COMPONENT_PACKAGES>
  <BPD_ITEMS/>
  <COLOR_RANGES/>
  <SHOW_EXPANDED>0</SHOW_EXPANDED>
  <LINKED_VALUES/>
  <FILE_METADATA/>
 </CONFIG_FIELDS_ITEM>
</CONFIG_FIELDS><CONFIG_GROUPS>
 <CONFIG_GROUPS_ITEM>
  <APP_LABEL>
   <T_LABEL>
    <APP_LANG_ID>0</APP_LANG_ID>
    <APP_LABEL_ID>-3985231</APP_LABEL_ID>
    <LABEL_TEXT>General Info</LABEL_TEXT>
   </T_LABEL>
   <T_LABEL>
    <APP_LANG_ID>1</APP_LANG_ID>
    <APP_LABEL_ID>-3985231</APP_LABEL_ID>
    <LABEL_TEXT>General Info</LABEL_TEXT>
   </T_LABEL>
   <T_LABEL>
    <APP_LANG_ID>5</APP_LANG_ID>
    <APP_LABEL_ID>-3985231</APP_LABEL_ID>
    <LABEL_TEXT>Îñíîâíàÿ Èíôîðìàöèÿ</LABEL_TEXT>
   </T_LABEL>
   <T_LABEL>
    <APP_LANG_ID>10</APP_LANG_ID>
    <APP_LABEL_ID>-3985231</APP_LABEL_ID>
    <LABEL_TEXT>General Info</LABEL_TEXT>
   </T_LABEL>
  </APP_LABEL>
  <CONFIG_GROUP_ID>1001220487</CONFIG_GROUP_ID>
  <DESCRIPTION>Test1_GENERAL_INFO</DESCRIPTION>
  <IS_EXTERNAL_GROUP>0</IS_EXTERNAL_GROUP>
  <IS_MASTER_TAB>1</IS_MASTER_TAB>
  <IS_XITOR_CONTAINER>0</IS_XITOR_CONTAINER>
  <STATIC_ID>0</STATIC_ID>
  <ALLOW_WEBCAM_AND_MIC>0</ALLOW_WEBCAM_AND_MIC>
  <TRACKOR_TYPE>Test1</TRACKOR_TYPE>
  <CONFIG_ELEM_XREFS>
   <T_CF_TAB_ELEM_XREF>
    <CONFIG_GROUP_ID>1001220487</CONFIG_GROUP_ID>
    <ROW_POS>2</ROW_POS>
    <COL_POS>1</COL_POS>
    <CONFIG_ELEMENT_ID>1004378456</CONFIG_ELEMENT_ID>
    <CONFIG_ELEMENT_TYPE_ID>1</CONFIG_ELEMENT_TYPE_ID>
    <ELEM_WIDTH>180</ELEM_WIDTH>
    <COLS_SPAN>1</COLS_SPAN>
    <IS_REQUIRED_BY_TAB>0</IS_REQUIRED_BY_TAB>
    <TEXT_LABELS/>
    <CONFIG_FIELDS>
     <T_CONFIG_FIELD>
      <APP_LABEL>
       <T_LABEL>
        <APP_LANG_ID>0</APP_LANG_ID>
        <APP_LABEL_ID>-3985246</APP_LABEL_ID>
        <LABEL_TEXT>Text</LABEL_TEXT>
       </T_LABEL>
       <T_LABEL>
        <APP_LANG_ID>1</APP_LANG_ID>
        <APP_LABEL_ID>-3985246</APP_LABEL_ID>
        <LABEL_TEXT>Text</LABEL_TEXT>
       </T_LABEL>
       <T_LABEL>
        <APP_LANG_ID>5</APP_LANG_ID>
        <APP_LABEL_ID>-3985246</APP_LABEL_ID>
        <LABEL_TEXT>Text</LABEL_TEXT>
       </T_LABEL>
       <T_LABEL>
        <APP_LANG_ID>10</APP_LANG_ID>
        <APP_LABEL_ID>-3985246</APP_LABEL_ID>
        <LABEL_TEXT>Text</LABEL_TEXT>
       </T_LABEL>
       <T_LABEL>
        <APP_LANG_ID>20</APP_LANG_ID>
        <APP_LABEL_ID>-3985246</APP_LABEL_ID>
        <LABEL_TEXT>Text</LABEL_TEXT>
       </T_LABEL>
      </APP_LABEL>
      <CONFIG_FIELD_ID>10010522178</CONFIG_FIELD_ID>
      <CONFIG_FIELD_NAME>T1_TEXT</CONFIG_FIELD_NAME>
      <DATA_TYPE>0</DATA_TYPE>
      <FIELD_SIZE>1000</FIELD_SIZE>
      <FIELD_WIDTH>180</FIELD_WIDTH>
      <GRID_COLUMN_WIDTH>160</GRID_COLUMN_WIDTH>
      <IMAGE_ROTATE>0</IMAGE_ROTATE>
      <IS_IMAGE_EXTRACT_METADATA>0</IS_IMAGE_EXTRACT_METADATA>
      <IS_LOCKABLE>0</IS_LOCKABLE>
      <IS_MANDATORY>0</IS_MANDATORY>
      <IS_MY_THINGS_MARKER>0</IS_MY_THINGS_MARKER>
      <IS_READ_ONLY>0</IS_READ_ONLY>
      <IS_SEPARATE_THOUSANDS>0</IS_SEPARATE_THOUSANDS>
      <IS_STATIC>0</IS_STATIC>
      <IS_TWO_COLS_SPAN>0</IS_TWO_COLS_SPAN>
      <LOG_BLOB_CHANGES>0</LOG_BLOB_CHANGES>
      <PARENS_FOR_NEGATIVE>0</PARENS_FOR_NEGATIVE>
      <SHORT_NAME_LABEL/>
      <STORE_IN_CLOUD>0</STORE_IN_CLOUD>
      <USE_IN_MY_THINGS_FILTER>0</USE_IN_MY_THINGS_FILTER>
      <TRACKOR_TYPE>Test1</TRACKOR_TYPE>
      <IS_SHOW_SECONDS>0</IS_SHOW_SECONDS>
      <PROGRAM_ID>10009255</PROGRAM_ID>
      <IS_NOT_CLONE_FIELD_VALUE>0</IS_NOT_CLONE_FIELD_VALUE>
      <IS_NOT_CLONE_LOCKS>0</IS_NOT_CLONE_LOCKS>
      <IS_UPLOAD_TO_S3_DIRECTLY>0</IS_UPLOAD_TO_S3_DIRECTLY>
      <IS_SUPPORT_BARCODE>0</IS_SUPPORT_BARCODE>
      <IS_VALIDATION_ENABLED>0</IS_VALIDATION_ENABLED>
      <ERROR_MESSAGE_LABEL/>
      <COMPONENT_PACKAGES>
       <T_BPL_COMP_PKG>
        <COMPONENT_ID>5</COMPONENT_ID>
        <OBJECT_ID>10010522178</OBJECT_ID>
        <COMPONENTS_PACKAGE_ID>171954</COMPONENTS_PACKAGE_ID>
        <NAME>TEST1</NAME>
        <PROGRAM_ID>10009255</PROGRAM_ID>
        <BPD_ITEMS/>
       </T_BPL_COMP_PKG>
      </COMPONENT_PACKAGES>
      <BPD_ITEMS/>
      <COLOR_RANGES/>
      <SHOW_EXPANDED>0</SHOW_EXPANDED>
      <LINKED_VALUES/>
      <FILE_METADATA/>
     </T_CONFIG_FIELD>
    </CONFIG_FIELDS>
    <WP_TASK_NAME/>
   </T_CF_TAB_ELEM_XREF>
   <T_CF_TAB_ELEM_XREF>
    <CONFIG_GROUP_ID>1001220487</CONFIG_GROUP_ID>
    <ROW_POS>1</ROW_POS>
    <COL_POS>1</COL_POS>
    <CONFIG_ELEMENT_ID>1004378437</CONFIG_ELEMENT_ID>
    <CONFIG_ELEMENT_TYPE_ID>1</CONFIG_ELEMENT_TYPE_ID>
    <ELEM_WIDTH>180</ELEM_WIDTH>
    <COLS_SPAN>1</COLS_SPAN>
    <IS_REQUIRED_BY_TAB>0</IS_REQUIRED_BY_TAB>
    <TEXT_LABELS/>
    <CONFIG_FIELDS>
     <T_CONFIG_FIELD>
      <APP_LABEL>
       <T_LABEL>
        <APP_LANG_ID>0</APP_LANG_ID>
        <APP_LABEL_ID>-3985229</APP_LABEL_ID>
        <LABEL_TEXT>Test1</LABEL_TEXT>
       </T_LABEL>
       <T_LABEL>
        <APP_LANG_ID>1</APP_LANG_ID>
        <APP_LABEL_ID>-3985229</APP_LABEL_ID>
        <LABEL_TEXT>Test1 ID</LABEL_TEXT>
       </T_LABEL>
       <T_LABEL>
        <APP_LANG_ID>5</APP_LANG_ID>
        <APP_LABEL_ID>-3985229</APP_LABEL_ID>
        <LABEL_TEXT>Test1</LABEL_TEXT>
       </T_LABEL>
       <T_LABEL>
        <APP_LANG_ID>10</APP_LANG_ID>
        <APP_LABEL_ID>-3985229</APP_LABEL_ID>
        <LABEL_TEXT>Test1</LABEL_TEXT>
       </T_LABEL>
       <T_LABEL>
        <APP_LANG_ID>20</APP_LANG_ID>
        <APP_LABEL_ID>-3985229</APP_LABEL_ID>
        <LABEL_TEXT>Test1</LABEL_TEXT>
       </T_LABEL>
      </APP_LABEL>
      <CONFIG_FIELD_ID>10010522158</CONFIG_FIELD_ID>
      <CONFIG_FIELD_NAME>XITOR_KEY</CONFIG_FIELD_NAME>
      <DATA_TYPE>0</DATA_TYPE>
      <DESCRIPTION>TRACKOR.TRACKOR_KEY</DESCRIPTION>
      <FIELD_SIZE>255</FIELD_SIZE>
      <FIELD_WIDTH>180</FIELD_WIDTH>
      <GRID_COLUMN_WIDTH>160</GRID_COLUMN_WIDTH>
      <IMAGE_ROTATE>0</IMAGE_ROTATE>
      <IS_IMAGE_EXTRACT_METADATA>0</IS_IMAGE_EXTRACT_METADATA>
      <IS_LOCKABLE>0</IS_LOCKABLE>
      <IS_MANDATORY>1</IS_MANDATORY>
      <IS_MY_THINGS_MARKER>0</IS_MY_THINGS_MARKER>
      <IS_READ_ONLY>0</IS_READ_ONLY>
      <IS_SEPARATE_THOUSANDS>0</IS_SEPARATE_THOUSANDS>
      <IS_STATIC>1</IS_STATIC>
      <IS_TWO_COLS_SPAN>0</IS_TWO_COLS_SPAN>
      <LOG_BLOB_CHANGES>0</LOG_BLOB_CHANGES>
      <PARENS_FOR_NEGATIVE>0</PARENS_FOR_NEGATIVE>
      <SHORT_NAME_LABEL/>
      <STORE_IN_CLOUD>0</STORE_IN_CLOUD>
      <USE_IN_MY_THINGS_FILTER>0</USE_IN_MY_THINGS_FILTER>
      <TRACKOR_TYPE>Test1</TRACKOR_TYPE>
      <IS_SHOW_SECONDS>0</IS_SHOW_SECONDS>
      <PROGRAM_ID>10009255</PROGRAM_ID>
      <IS_NOT_CLONE_FIELD_VALUE>0</IS_NOT_CLONE_FIELD_VALUE>
      <IS_NOT_CLONE_LOCKS>0</IS_NOT_CLONE_LOCKS>
      <IS_UPLOAD_TO_S3_DIRECTLY>0</IS_UPLOAD_TO_S3_DIRECTLY>
      <IS_SUPPORT_BARCODE>0</IS_SUPPORT_BARCODE>
      <IS_VALIDATION_ENABLED>0</IS_VALIDATION_ENABLED>
      <ERROR_MESSAGE_LABEL/>
      <COMPONENT_PACKAGES/>
      <BPD_ITEMS/>
      <COLOR_RANGES/>
      <SHOW_EXPANDED>0</SHOW_EXPANDED>
      <LINKED_VALUES/>
      <FILE_METADATA/>
     </T_CONFIG_FIELD>
    </CONFIG_FIELDS>
    <WP_TASK_NAME/>
   </T_CF_TAB_ELEM_XREF>
  </CONFIG_ELEM_XREFS>
  <CONFIG_GROUP_PARAMS/>
  <XITOR_CLASS/>
  <BPD_ITEMS/>
  <PROGRAM_ID>10009255</PROGRAM_ID>
  <COMPONENT_PACKAGES>
   <T_BPL_COMP_PKG>
    <COMPONENT_ID>6</COMPONENT_ID>
    <OBJECT_ID>1001220487</OBJECT_ID>
    <COMPONENTS_PACKAGE_ID>171954</COMPONENTS_PACKAGE_ID>
    <NAME>TEST1</NAME>
    <PROGRAM_ID>10009255</PROGRAM_ID>
    <BPD_ITEMS/>
   </T_BPL_COMP_PKG>
  </COMPONENT_PACKAGES>
  <ELEMENT_UI_ACTIONS/>
 </CONFIG_GROUPS_ITEM>
</CONFIG_GROUPS><IMPORT>
 <IMPORT_ITEM>
  <DATE_FORMAT>MM/DD/YYYY</DATE_FORMAT>
  <DEFAULT_ACTION>3</DEFAULT_ACTION>
  <FIELD_DELIMITER>
   <DELIMITER>[44]</DELIMITER>
   <DESCRIPTION>Comma</DESCRIPTION>
  </FIELD_DELIMITER>
  <IMP_ACTION>3</IMP_ACTION>
  <IMP_FILE_TYPE>
   <IMP_FILE_TYPE_ID>1</IMP_FILE_TYPE_ID>
   <IMP_FILE_TYPE>CSV</IMP_FILE_TYPE>
  </IMP_FILE_TYPE>
  <IMP_SPEC_ID>1001026571</IMP_SPEC_ID>
  <KEEP_SQL_LOADER_EXT_TABLE>0</KEEP_SQL_LOADER_EXT_TABLE>
  <LINE_DELIMITER>
   <DELIMITER>[44]</DELIMITER>
   <DESCRIPTION>Comma</DESCRIPTION>
  </LINE_DELIMITER>
  <NAME>test1</NAME>
  <STRING_QUOTE>
   <DELIMITER>[34]</DELIMITER>
   <DESCRIPTION>Double Quotes</DESCRIPTION>
  </STRING_QUOTE>
  <USE_SQL_LOADER>0</USE_SQL_LOADER>
  <IMP_COLUMNS>
   <T_IMP_COLUMN>
    <IMP_COLUMN_ID>1001141111</IMP_COLUMN_ID>
    <ORDER_NUMBER>0</ORDER_NUMBER>
    <NAME>ID</NAME>
   </T_IMP_COLUMN>
   <T_IMP_COLUMN>
    <IMP_COLUMN_ID>1001141112</IMP_COLUMN_ID>
    <ORDER_NUMBER>1</ORDER_NUMBER>
    <NAME>TEXT</NAME>
   </T_IMP_COLUMN>
  </IMP_COLUMNS>
  <IMP_ENTITYS>
   <T_IMP_ENTITY>
    <ENTITY_NAME>Test1</ENTITY_NAME>
    <IMP_ENTITY_ID>1001034631</IMP_ENTITY_ID>
    <IMP_SPEC_ID>1001026571</IMP_SPEC_ID>
    <ORDER_NUMBER>0</ORDER_NUMBER>
    <SQL_TEXT>select xitor_id from xitor where xitor_key = &apos;:p_key&apos;;</SQL_TEXT>
    <TRACKOR_TYPE>Test1</TRACKOR_TYPE>
    <IMP_ENTITY_PARAMS>
     <T_IMP_ENTITY_PARAM>
      <IMP_COLUMN_ID>1001141111</IMP_COLUMN_ID>
      <IMP_ENTITY_ID>1001034631</IMP_ENTITY_ID>
      <IMP_ENTITY_PARAM_ID>1001062358</IMP_ENTITY_PARAM_ID>
      <SQL_PARAMETER>p_key</SQL_PARAMETER>
     </T_IMP_ENTITY_PARAM>
    </IMP_ENTITY_PARAMS>
    <IMP_DATA_MAPS>
     <T_IMP_DATA_MAP>
      <DATA_MAP_NAME>TEXT</DATA_MAP_NAME>
      <IMP_COLUMN_ID>1001141112</IMP_COLUMN_ID>
      <IMP_DATA_MAP_ID>1001108213</IMP_DATA_MAP_ID>
      <IMP_DATA_TYPE_ID>1</IMP_DATA_TYPE_ID>
      <IMP_DATA_TYPE>Configurable Field</IMP_DATA_TYPE>
      <IMP_ENTITY_ID>1001034631</IMP_ENTITY_ID>
      <IMP_SPEC_ID>1001026571</IMP_SPEC_ID>
      <ORDER_NUMBER>0</ORDER_NUMBER>
      <IMP_DATA_MAP_PARAMS/>
      <IMP_DATA_MAP_PARAM_VALS>
       <T_IMP_DATA_MAP_PARAM_VAL>
        <IMP_DATA_TYPE_PARAM_ID>1</IMP_DATA_TYPE_PARAM_ID>
        <IMP_DATA_TYPE_ID>1</IMP_DATA_TYPE_ID>
        <IMP_DATA_TYPE_MAP_ID>1001108213</IMP_DATA_TYPE_MAP_ID>
        <IMP_DATA_TYPE_PARAM_VALUE_ID>1001347023</IMP_DATA_TYPE_PARAM_VALUE_ID>
        <VALUE>10010522178</VALUE>
        <DISPLAY_VALUE>T1Text - T1_TEXT</DISPLAY_VALUE>
        <PROGRAM_ID>10009255</PROGRAM_ID>
        <CF_NAME>T1_TEXT</CF_NAME>
        <CF_TRACKOR_TYPE>Test1</CF_TRACKOR_TYPE>
       </T_IMP_DATA_MAP_PARAM_VAL>
       <T_IMP_DATA_MAP_PARAM_VAL>
        <IMP_DATA_TYPE_PARAM_ID>16</IMP_DATA_TYPE_PARAM_ID>
        <IMP_DATA_TYPE_ID>1</IMP_DATA_TYPE_ID>
        <IMP_DATA_TYPE_MAP_ID>1001108213</IMP_DATA_TYPE_MAP_ID>
        <IMP_DATA_TYPE_PARAM_VALUE_ID>1001347024</IMP_DATA_TYPE_PARAM_VALUE_ID>
        <VALUE>0</VALUE>
        <DISPLAY_VALUE>0</DISPLAY_VALUE>
        <PROGRAM_ID>10009255</PROGRAM_ID>
       </T_IMP_DATA_MAP_PARAM_VAL>
       <T_IMP_DATA_MAP_PARAM_VAL>
        <IMP_DATA_TYPE_PARAM_ID>17</IMP_DATA_TYPE_PARAM_ID>
        <IMP_DATA_TYPE_ID>1</IMP_DATA_TYPE_ID>
        <IMP_DATA_TYPE_MAP_ID>1001108213</IMP_DATA_TYPE_MAP_ID>
        <IMP_DATA_TYPE_PARAM_VALUE_ID>1001347025</IMP_DATA_TYPE_PARAM_VALUE_ID>
        <VALUE>0</VALUE>
        <DISPLAY_VALUE>0</DISPLAY_VALUE>
        <PROGRAM_ID>10009255</PROGRAM_ID>
       </T_IMP_DATA_MAP_PARAM_VAL>
      </IMP_DATA_MAP_PARAM_VALS>
     </T_IMP_DATA_MAP>
    </IMP_DATA_MAPS>
    <IMP_ENTITY_REQ_FIELDS>
     <T_IMP_ENTITY_REQ_FIELD>
      <IMP_ENTITY_ID>1001034631</IMP_ENTITY_ID>
      <IMP_ENTITY_REQ_FIELD_ID>1001099774</IMP_ENTITY_REQ_FIELD_ID>
      <VALUE>AUTO_GENERATION</VALUE>
      <XITOR_REQ_FIELD>TRACKOR_KEY</XITOR_REQ_FIELD>
      <REQ_FIELD_PARAMS/>
     </T_IMP_ENTITY_REQ_FIELD>
     <T_IMP_ENTITY_REQ_FIELD>
      <IMP_ENTITY_ID>1001034631</IMP_ENTITY_ID>
      <IMP_ENTITY_REQ_FIELD_ID>1001099775</IMP_ENTITY_REQ_FIELD_ID>
      <VALUE>PROGRAM_ID</VALUE>
      <XITOR_REQ_FIELD>PROGRAM_ID</XITOR_REQ_FIELD>
      <REQ_FIELD_PARAMS/>
     </T_IMP_ENTITY_REQ_FIELD>
    </IMP_ENTITY_REQ_FIELDS>
   </T_IMP_ENTITY>
  </IMP_ENTITYS>
  <PROGRAM_ID>10009255</PROGRAM_ID>
  <TIME_FORMAT>HH24:MI:SS</TIME_FORMAT>
  <VALIDATE_DATA_MODE_ID>1</VALIDATE_DATA_MODE_ID>
  <COMPONENT_PACKAGES>
   <T_BPL_COMP_PKG>
    <COMPONENT_ID>1</COMPONENT_ID>
    <OBJECT_ID>1001026571</OBJECT_ID>
    <COMPONENTS_PACKAGE_ID>171954</COMPONENTS_PACKAGE_ID>
    <NAME>TEST1</NAME>
    <PROGRAM_ID>10009255</PROGRAM_ID>
    <BPD_ITEMS/>
   </T_BPL_COMP_PKG>
  </COMPONENT_PACKAGES>
  <BPD_ITEMS/>
 </IMPORT_ITEM>
</IMPORT>
</COMPONENTS>